mkdocs_flavorwheel_plugin/__init__.py
mkdocs_flavorwheel_plugin/plugin.py
mkdocs_flavorwheel_plugin-0.0.6.dist-info/LICENSE
mkdocs_flavorwheel_plugin-0.0.6.dist-info/METADATA
mkdocs_flavorwheel_plugin-0.0.6.dist-info/WHEEL
mkdocs_flavorwheel_plugin-0.0.6.dist-info/entry_points.txt
mkdocs_flavorwheel_plugin-0.0.6.dist-info/top_level.txt
mkdocs_flavorwheel_plugin-0.0.6.dist-info/RECORD
